connect/.data/connect_reports/.github/workflows/build.yml
connect/.data/connect_reports/.gitignore
connect/.data/connect_reports/LICENSE
connect/.data/connect_reports/README.md
connect/.data/connect_reports/poetry.lock
connect/.data/connect_reports/pyproject.toml
connect/.data/connect_reports/reports/__init__.py
connect/.data/connect_reports/reports/billing_requests/Readme.md
connect/.data/connect_reports/reports/billing_requests/__init__.py
connect/.data/connect_reports/reports/billing_requests/entrypoint.py
connect/.data/connect_reports/reports/billing_requests/templates/xlsx/template.xlsx
connect/.data/connect_reports/reports/billing_requests_line_item/Readme.md
connect/.data/connect_reports/reports/billing_requests_line_item/__init__.py
connect/.data/connect_reports/reports/billing_requests_line_item/entrypoint.py
connect/.data/connect_reports/reports/billing_requests_line_item/templates/xlsx/template.xlsx
connect/.data/connect_reports/reports/contract_list/Readme.md
connect/.data/connect_reports/reports/contract_list/__init__.py
connect/.data/connect_reports/reports/contract_list/entrypoint.py
connect/.data/connect_reports/reports/contract_list/templates/xlsx/template.xlsx
connect/.data/connect_reports/reports/customers_list/Readme.md
connect/.data/connect_reports/reports/customers_list/__init__.py
connect/.data/connect_reports/reports/customers_list/entrypoint.py
connect/.data/connect_reports/reports/customers_list/templates/xlsx/template.xlsx
connect/.data/connect_reports/reports/executive_fullfilment_requests/Readme.md
connect/.data/connect_reports/reports/executive_fullfilment_requests/__init__.py
connect/.data/connect_reports/reports/executive_fullfilment_requests/constants.py
connect/.data/connect_reports/reports/executive_fullfilment_requests/entrypoint.py
connect/.data/connect_reports/reports/executive_fullfilment_requests/templates/pdf/img/ClouBlue-Logo.png
connect/.data/connect_reports/reports/executive_fullfilment_requests/templates/pdf/template.css
connect_cli-40.6.dist-info/METADATA
connect_cli-40.6.dist-info/WHEEL
connect_cli-40.6.dist-info/entry_points.txt
connect_cli-40.6.dist-info/licenses/LICENSE
connect_cli-40.6.dist-info/RECORD
