Metadata-Version: 2.4
Name: connect-cli
Version: 40.6
Summary: CloudBlue Connect Command Line Interface
License: Apache-2.0
License-File: LICENSE
Keywords: fulfillment,command,line,interface,utility,cli,vendor,connect,cloudblue
Author: CloudBlue LLC
Requires-Python: >=3.10,<4
Classifier: Development Status :: 5 - Production/Stable
Classifier: Environment :: Console
Classifier: License :: OSI Approved :: Apache Software License
Classifier: Operating System :: POSIX :: Linux
Classifier: Programming Language :: Python :: 3
Classifier: Programming Language :: Python :: 3.10
Classifier: Programming Language :: Python :: 3.11
Classifier: Programming Language :: Python :: 3.12
Classifier: Programming Language :: Python :: 3.13
Classifier: Programming Language :: Python :: 3.14
Classifier: Programming Language :: Python :: 3.8
Classifier: Programming Language :: Python :: 3.9
Classifier: Topic :: Utilities
Requires-Dist: Jinja2 (>=3.1.2,<4.0.0)
Requires-Dist: click (>=8.1.3,<9.0.0)
Requires-Dist: connect-eaas-core (>=37.0)
Requires-Dist: connect-markdown-renderer (>=3,<4)
Requires-Dist: connect-openapi-client (>=29)
Requires-Dist: connect-reports-core (==26.*)
Requires-Dist: fs (>=2.4.12,<3.0.0)
Requires-Dist: interrogatio (>=2.3.1,<3.0.0)
Requires-Dist: iso3166 (>=1.0.1,<2.0.0)
Requires-Dist: jinja2-time (>=0.2.0,<0.3.0)
Requires-Dist: openpyxl (>=3.0.7,<4.0.0)
Requires-Dist: phonenumbers (>=8.12.19,<9.0.0)
Requires-Dist: poetry-core (>=1.3.0,<2.0.0)
Requires-Dist: pyyaml (>=6.0,<7.0)
Requires-Dist: requests (>=2.25.1,<3.0.0)
Requires-Dist: rich (>=12.4.1,<13.0.0)
Requires-Dist: toml (>=0.10.2,<0.11.0)
Requires-Dist: uvloop (>=0.22.0,<0.23.0) ; sys_platform == "linux" or sys_platform == "darwin"
Project-URL: Documentation, https://connect.cloudblue.com/community/sdk/cli/
Project-URL: Homepage, https://connect.cloudblue.com
Project-URL: Repository, https://github.com/cloudblue/connect-cli
